pyramid_marrowmailer/__init__.py
pyramid_marrowmailer/tests.py
pyramid_marrowmailer-0.2.dist-info/METADATA
pyramid_marrowmailer-0.2.dist-info/RECORD
pyramid_marrowmailer-0.2.dist-info/WHEEL
pyramid_marrowmailer-0.2.dist-info/entry_points.txt
pyramid_marrowmailer-0.2.dist-info/top_level.txt
