Metadata-Version: 2.1
Name: pyramid-marrowmailer
Version: 0.2
Summary: Pyramid integration package for marrow.mailer, formerly known as TurboMail
Home-page: https://github.com/iElectric/pyramid_marrowmailer
Author: 
Author-email: domen@dev.si
License: BSD
Keywords: web wsgi pylons pyramid
Platform: UNKNOWN
Classifier: Programming Language :: Python
Classifier: Framework :: Pyramid
Provides-Extra: test
Requires-Dist: pyramid
Requires-Dist: pyramid-tm
Requires-Dist: marrow.mailer
Requires-Dist: setuptools
Requires-Dist: transaction
Provides-Extra: test
Requires-Dist: nose; extra == 'test'
Requires-Dist: coverage; extra == 'test'
Requires-Dist: setuptools-flakes; extra == 'test'
Requires-Dist: pep8; extra == 'test'
